AUTHORS
BUGS.md
CHANGES.rst
LICENSE
MANIFEST.in
README.rst
TODO.md
setup.py
dve/__init__.py
dve.egg-info/PKG-INFO
dve.egg-info/SOURCES.txt
dve.egg-info/dependency_links.txt
dve.egg-info/entry_points.txt
dve.egg-info/top_level.txt
dve/data/__init__.py
dve/data/table.py
dve/io/__init__.py
dve/io/lock.py
dve/io/table.py
dve/qt/__init__.py
dve/qt/delegates/__init__.py
dve/qt/delegates/table.py
dve/qt/models/__init__.py
dve/qt/models/table.py
dve/qt/widgets/__init__.py
dve/qt/widgets/tabs/__init__.py
dve/qt/widgets/tabs/table.py